setup.py
CSV_Splitter_az.egg-info/PKG-INFO
CSV_Splitter_az.egg-info/SOURCES.txt
CSV_Splitter_az.egg-info/dependency_links.txt
CSV_Splitter_az.egg-info/requires.txt
CSV_Splitter_az.egg-info/top_level.txt
csv_splitter/CSV_Splitter.py
csv_splitter/__init__.py