Metadata-Version: 1.0
Name: CSV-Splitter-az
Version: 0.1
Summary: A package to process CSV files in chunks.
Home-page: https://github.com/kfvl083_azu/CSV_splitter
Author: Chinthamani
Author-email: msindhu060@gmail.com
License: UNKNOWN
Platform: UNKNOWN
